iconfonts/__init__.py
iconfonts/extension.py
markdown_icons-3.0.dist-info/LICENSE
markdown_icons-3.0.dist-info/METADATA
markdown_icons-3.0.dist-info/WHEEL
markdown_icons-3.0.dist-info/entry_points.txt
markdown_icons-3.0.dist-info/top_level.txt
markdown_icons-3.0.dist-info/RECORD
