Metadata-Version: 2.2
Name: markdown-icons
Version: 3.0
Summary: Markdown extension to display icons
Author-email: Tom Hubrecht <pypi@mail.hubrecht.ovh>, Eric Eastwood <contact@ericeastwood.com>
License: Copyright 2024 Tom Hubrecht
Project-URL: Homepage, https://github.com/Tom-Hubrecht/markdown-icons
Project-URL: Repository, https://github.com/Tom-Hubrecht/markdown-icons
Project-URL: Issues, https://github.com/Tom-Hubrecht/markdown-icons/issues
Keywords: markdown,icons,fontawesome,bootstrap
Classifier: Development Status :: 5 - Production/Stable
Classifier: Environment :: Web Environment
Classifier: License :: OSI Approved :: MIT License
Classifier: Programming Language :: Python :: 3
License-File: LICENSE
Requires-Dist: markdown
